CrappyPython/__init__.py
CrappyPython/setup.py
CrappyPython-0.0.1.dist-info/METADATA
CrappyPython-0.0.1.dist-info/WHEEL
CrappyPython-0.0.1.dist-info/top_level.txt
CrappyPython-0.0.1.dist-info/RECORD
